{ "indexes" : [ { "v" : 1, "key" : { "_id" : 1 }, "name" : "_id_", "ns" : "ideapod-site-development.ideas" }, { "v" : 1, "key" : { "connections._idea" : 1 }, "name" : "connections._idea_1", "ns" : "ideapod-site-development.ideas", "background" : true, "safe" : null }, { "v" : 1, "key" : { "_user" : 1 }, "name" : "_user_1", "ns" : "ideapod-site-development.ideas", "background" : true, "safe" : null }, { "v" : 1, "key" : { "score" : 1 }, "name" : "score_1", "ns" : "ideapod-site-development.ideas", "background" : true, "safe" : null } ] }